<annotation>
	<folder></folder>
	<filename>icu-room_6_jpg.rf.66ee5914db90a3593a016d6747b697fd.jpg</filename>
	<path>icu-room_6_jpg.rf.66ee5914db90a3593a016d6747b697fd.jpg</path>
	<source>
		<database>roboflow.ai</database>
	</source>
	<size>
		<width>640</width>
		<height>640</height>
		<depth>3</depth>
	</size>
	<segmented>0</segmented>
	<object>
		<name>cardiac_monitor</name>
		<pose>Unspecified</pose>
		<truncated>0</truncated>
		<difficult>0</difficult>
		<occluded>0</occluded>
		<bndbox>
			<xmin>95</xmin>
			<xmax>164</xmax>
			<ymin>199</ymin>
			<ymax>285</ymax>
		</bndbox>
	</object>
	<object>
		<name>patient_bed</name>
		<pose>Unspecified</pose>
		<truncated>0</truncated>
		<difficult>0</difficult>
		<occluded>0</occluded>
		<bndbox>
			<xmin>191</xmin>
			<xmax>399</xmax>
			<ymin>299</ymin>
			<ymax>508</ymax>
		</bndbox>
	</object>
	<object>
		<name>cardiac_monitor</name>
		<pose>Unspecified</pose>
		<truncated>0</truncated>
		<difficult>0</difficult>
		<occluded>0</occluded>
		<bndbox>
			<xmin>176</xmin>
			<xmax>225</xmax>
			<ymin>180</ymin>
			<ymax>251</ymax>
		</bndbox>
	</object>
</annotation>
