<annotation>
	<folder></folder>
	<filename>oxygenmasks73_jpg.rf.7f76fd9b18caae20088eb0501014fec1.jpg</filename>
	<path>oxygenmasks73_jpg.rf.7f76fd9b18caae20088eb0501014fec1.jpg</path>
	<source>
		<database>roboflow.ai</database>
	</source>
	<size>
		<width>640</width>
		<height>640</height>
		<depth>3</depth>
	</size>
	<segmented>0</segmented>
	<object>
		<name>oxygen_mask</name>
		<pose>Unspecified</pose>
		<truncated>0</truncated>
		<difficult>0</difficult>
		<occluded>0</occluded>
		<bndbox>
			<xmin>240</xmin>
			<xmax>364</xmax>
			<ymin>241</ymin>
			<ymax>409</ymax>
		</bndbox>
	</object>
	<object>
		<name>patient</name>
		<pose>Unspecified</pose>
		<truncated>0</truncated>
		<difficult>0</difficult>
		<occluded>0</occluded>
		<bndbox>
			<xmin>134</xmin>
			<xmax>561</xmax>
			<ymin>160</ymin>
			<ymax>608</ymax>
		</bndbox>
	</object>
</annotation>
